kompress/__init__.py
kompress/compat.py
kompress/py.typed
kompress/tar.py
kompress/utils.py
kompress/zip.py
kompress/tests/kompress.py
kompress/tests/zippath.py
kompress/tests/structure_data/gdpr_export.tar.gz
kompress/tests/structure_data/gdpr_export.zip
kompress/tests/structure_data/with_leading_dot.tar.gz
kompress-0.3.20250823.dist-info/METADATA
kompress-0.3.20250823.dist-info/WHEEL
kompress-0.3.20250823.dist-info/licenses/LICENSE
kompress-0.3.20250823.dist-info/RECORD
