Metadata-Version: 2.4
Name: kompress
Version: 0.3.20250823
Summary: pathlib.Path adapters to transparently read data from compressed files and folders
Project-URL: Homepage, https://github.com/karlicoss/kompress
Author-email: "Dima Gerasimov (@karlicoss)" <karlicoss@gmail.com>
Maintainer-email: "Dima Gerasimov (@karlicoss)" <karlicoss@gmail.com>
License: MIT License
License-File: LICENSE
Requires-Python: >=3.10
Requires-Dist: typing-extensions
Provides-Extra: lz4
Requires-Dist: lz4; extra == 'lz4'
Provides-Extra: zstd
Requires-Dist: zstandard; (python_version < '3.14') and extra == 'zstd'
